README.rst
setup.py
pmll/__init__.py
pmll/base.py
pmll/data.py
pmll/six.py
pmll/utils.py
pmll.egg-info/PKG-INFO
pmll.egg-info/SOURCES.txt
pmll.egg-info/dependency_links.txt
pmll.egg-info/top_level.txt
pmll/feature/__init__.py
pmll/feature/models.py
pmll/feature/operations.py
pmll/feature/tests.py
pmll/metrics/__init__.py
pmll/metrics/base.py
pmll/metrics/tests.py
pmll/regression/__init__.py
pmll/regression/least_squares.py
pmll/regression/tests/__init__.py
pmll/regression/tests/test_least_squares.py
pmll/tests/__init__.py
pmll/tests/test_base.py
pmll/tests/test_data.py