Metadata-Version: 1.1
Name: pmll
Version: 0.1.5
Summary: Python machine learning library
Home-page: https://github.com/pavlov99/pmll
Author: Kirill Pavlov
Author-email: kirill.pavlov@phystech.edu
License: MIT
Keywords: data mining
Platform: UNKNOWN
Classifier: Development Status :: 3 - Alpha
Classifier: Environment :: Console
Classifier: Intended Audience :: Science/Research
Classifier: License :: OSI Approved :: MIT License
Classifier: Natural Language :: English
Classifier: Operating System :: OS Independent
Classifier: Programming Language :: Python :: 2.7
Classifier: Programming Language :: Python :: 3.3
Classifier: Topic :: Scientific/Engineering :: Artificial Intelligence
Classifier: Topic :: Software Development :: Libraries
